examples/__init__.py
examples/fairseq/__init__.py
examples/fairseq/generate.py
examples/fairseq/interactive.py
examples/fairseq/train.py
examples/fairseq/criterions/__init__.py
examples/fairseq/criterions/masked_lm_moe.py
examples/fairseq/models/__init__.py
examples/fairseq/models/bert.py
examples/fairseq/models/language_modeling.py
examples/fairseq/models/machine_translation.py
examples/fairseq/models/retnet.py
examples/fairseq/tasks/__init__.py
examples/fairseq/tasks/pretraining.py
examples/fairseq/tasks/data/__init__.py
examples/fairseq/tasks/data/basic_loader.py
examples/fairseq/tasks/data/mlm_loader.py
examples/fairseq/tasks/data/utils.py
examples/fairseq/utils/__init__.py
examples/fairseq/utils/sparse_clip.py
torchscale/__init__.py
torchscale/architecture/__init__.py
torchscale/architecture/config.py
torchscale/architecture/decoder.py
torchscale/architecture/encoder.py
torchscale/architecture/encoder_decoder.py
torchscale/architecture/retnet.py
torchscale/architecture/utils.py
torchscale/component/__init__.py
torchscale/component/droppath.py
torchscale/component/embedding.py
torchscale/component/feedforward_network.py
torchscale/component/gate_linear_unit.py
torchscale/component/multihead_attention.py
torchscale/component/multiscale_retention.py
torchscale/component/multiway_network.py
torchscale/component/relative_position_bias.py
torchscale/component/rms_norm.py
torchscale/component/xpos_relative_position.py
torchscale/component/xmoe/__init__.py
torchscale/component/xmoe/global_groups.py
torchscale/component/xmoe/moe_layer.py
torchscale/component/xmoe/routing.py
torchscale/model/BEiT3.py
torchscale/model/__init__.py
torchscale-0.3.0.dist-info/LICENSE
torchscale-0.3.0.dist-info/METADATA
torchscale-0.3.0.dist-info/WHEEL
torchscale-0.3.0.dist-info/top_level.txt
torchscale-0.3.0.dist-info/RECORD
