Metadata-Version: 2.1
Name: torchscale
Version: 0.3.0
Summary: Transformers at any scale
Home-page: https://github.com/microsoft/torchscale
Author: TorchScale Team
Author-email: Shuming.Ma@microsoft.com
License: MIT
Keywords: Transformers at any scale
Classifier: Programming Language :: Python :: 3
Requires-Python: >=3.8.0
License-File: LICENSE
Requires-Dist: torch (>=1.8)
Requires-Dist: fairscale (==0.4.0)
Requires-Dist: timm (==0.6.13)
